LICENSE
MANIFEST.in
README.md
setup.cfg
setup.py
keen_dashboard/__init__.py
keen_dashboard/admin.py
keen_dashboard/apps.py
keen_dashboard/components.py
keen_dashboard/config.py
keen_dashboard/widgets.py
keen_dashboard.egg-info/PKG-INFO
keen_dashboard.egg-info/SOURCES.txt
keen_dashboard.egg-info/dependency_links.txt
keen_dashboard.egg-info/top_level.txt
keen_dashboard/static/admin/css/admin.base.css
keen_dashboard/static/admin/css/admin.error.404.css
keen_dashboard/static/admin/css/admin.form.css
keen_dashboard/static/admin/css/admin.list.css
keen_dashboard/static/admin/css/iframe.css
keen_dashboard/static/admin/img/blank-avatar.svg
keen_dashboard/static/admin/js/actions.js
keen_dashboard/static/admin/js/alertas.js
keen_dashboard/static/admin/js/autosize.min.js
keen_dashboard/static/admin/js/change_form.js
keen_dashboard/static/admin/js/change_list.js
keen_dashboard/static/admin/js/date.picker.br.js
keen_dashboard/static/admin/js/jquery.mask.min.js
keen_dashboard/static/admin/js/prepopulate_init.js
keen_dashboard/static/admin/js/search_field.js
keen_dashboard/static/dist/assets/css/style.bundle.css
keen_dashboard/static/dist/assets/css/style.bundle.js
keen_dashboard/static/dist/assets/css/pages/blog/grid-v2.css
keen_dashboard/static/dist/assets/css/pages/blog/grid-v2.js
keen_dashboard/static/dist/assets/css/pages/blog/grid.css
keen_dashboard/static/dist/assets/css/pages/blog/grid.js
keen_dashboard/static/dist/assets/css/pages/blog/list.css
keen_dashboard/static/dist/assets/css/pages/blog/list.js
keen_dashboard/static/dist/assets/css/pages/blog/post.css
keen_dashboard/static/dist/assets/css/pages/blog/post.js
keen_dashboard/static/dist/assets/css/pages/error/404-v1.css
keen_dashboard/static/dist/assets/css/pages/error/404-v1.js
keen_dashboard/static/dist/assets/css/pages/error/404-v2.css
keen_dashboard/static/dist/assets/css/pages/error/404-v2.js
keen_dashboard/static/dist/assets/css/pages/error/404-v3.css
keen_dashboard/static/dist/assets/css/pages/error/404-v3.js
keen_dashboard/static/dist/assets/css/pages/error/404-v4.css
keen_dashboard/static/dist/assets/css/pages/error/404-v4.js
